disprocos2/__init__.py
disprocos2/main.py
disprocos2/timer.py
disprocos2-0.1.0.dist-info/LICENCE.txt
disprocos2-0.1.0.dist-info/METADATA
disprocos2-0.1.0.dist-info/WHEEL
disprocos2-0.1.0.dist-info/entry_points.txt
disprocos2-0.1.0.dist-info/top_level.txt
disprocos2-0.1.0.dist-info/RECORD
