Metadata-Version: 2.1
Name: disprocos2
Version: 0.1.0
Summary: process the estimation of genetic distance
Author: YN
Author-email: emory@ex.edu.com
Classifier: Programming Language :: Python :: 3
Classifier: License :: OSI Approved :: MIT License
Classifier: Operating System :: OS Independent
Requires-Python: >=3.6
License-File: LICENCE.txt
